misc_items/switch/vsrc/sw.v
module sw (
    input  a,
    input  b,
    output c
);
  assign c = a ^ b;
endmodule

misc_items/switch/wave.vcd
$version Generated by VerilatedVcd $end
$timescale 1s $end
 $scope module TOP $end
  $var wire 1 # a $end
  $var wire 1 $ b $end
  $var wire 1 % c $end
  $scope module sw $end
   $var wire 1 # a $end
   $var wire 1 $ b $end
   $var wire 1 % c $end
  $upscope $end
 $upscope $end
$enddefinitions $end


#0
1#
1$
0%
#1
0#
1%
#2
0$
0%
#3
1$
1%
#4
1#
0%
#6
0#
0$
#7
1#
1%
#8
0#
0%
#12
1#
1%
#13
1$
0%
#14
0#
0$
#15
1#
1%
#16
0#
1$
#18
0$
0%
#19
1$
1%
#20
1#
0%
#21
0#
1%
#22
1#
0$
#25
1$
0%
#27
0#
1%
#29
1#
0$
#30
0#
1$
#31
0$
0%
#32
1#
1$
#33
0$
1%
#34
0#
0%
#35
1#
1$
#38
0$
1%
#42
0#
0%
#45
1$
1%
#46
1#
0%
#47
0#
1%
#48
0$
0%
#49
1#
1$
#50
0#
1%
#52
1#
0$
#54
0#
0%
#55
1#
1$
#56
0#
0$
#58
1$
1%
#59
1#
0%
#60
0$
1%
